{"name": "Description: 20200608_SO| Title:  | Text:  | Comments:  | File name: documents/20200608_SO_HoszeDM.xlsx | Uploaded at: 2023-04-30 12:55:41.521088+00:00", "title": "", "text_URL": "", "comments_URL": "", "children": [{"name": 3, "user_id": "Albora", "date": "2020-06-09 12:12:00+00:00", "thread": 3, "comment_level": 1, "coment": "Y quien dice que no queremos inmigrantes? Lo que no queremos son menas robando ni moritos viviendo de las ayudas. Y porque ahora los llaman \"migrantes\"? Es que la gente se ha vuelto imb\u00e9cil matters.  \u00bfverdad?", "argumentation": 1, "constructiveness": 0, "positive_stance": 0, "negative_stance": 1, "target_person": 0, "target_group": 1, "stereotype": 1, "sarcasm": 0, "mockery": 0, "insult": 0, "improper_language": 1, "aggressiveness": 0, "intolerance": 1, "toxicity": 1, "toxicity_level": 3, "children": [{"name": 10, "user_id": "oceaon3d", "date": "2020-06-09 12:31:00+00:00", "thread": 3, "comment_level": 2, "coment": "Tufillo a voxer que tumba...todo el atraso de lo peor del siglo XX es un mochilas.", "argumentation": 0, "constructiveness": 0, "positive_stance": 0, "negative_stance": 1, "target_person": 1, "target_group": 0, "stereotype": 0, "sarcasm": 0, "mockery": 1, "insult": 0, "improper_language": 0, "aggressiveness": 0, "intolerance": 0, "toxicity": 1, "toxicity_level": 1, "children": [{"name": 31, "user_id": "Albora", "date": "2020-06-09 13:22:00+00:00", "thread": 10, "comment_level": 2, "coment": "A estas alturas a\u00fan me tiran puntas de voxero?. Que siiiiii,  que lo soooooy. Y por eso me anulan en esta p\u00e1gina progremita. Pero mientras me dejen seguir\u00e9 opinando,  porque yo,  queridos m\u00edos,  os leo porque soy persona que amplias miras,  mientras que vosotros anulais lo que no os gusta leer a\u00fan cuando tengo raz\u00f3n. Radical fruit company.", "argumentation": 0, "constructiveness": 0, "positive_stance": 0, "negative_stance": 1, "target_person": 0, "target_group": 0, "stereotype": 0, "sarcasm": 1, "mockery": 1, "insult": 0, "improper_language": 0, "aggressiveness": 0, "intolerance": 0, "toxicity": 1, "toxicity_level": 1, "children": [{"name": 75, "user_id": "652149", "date": "2020-06-09 14:29:00+00:00", "thread": 31, "comment_level": 2, "coment": "Que tu madre te diga que tienes raz\u00f3n no implica que la tengas.", "argumentation": 0, "constructiveness": 0, "positive_stance": 0, "negative_stance": 0, "target_person": 1, "target_group": 0, "stereotype": 0, "sarcasm": 1, "mockery": 1, "insult": 0, "improper_language": 0, "aggressiveness": 0, "intolerance": 0, "toxicity": 1, "toxicity_level": 1}]}]}]}]}
